dvnv/__init__.py
dvnv/__main__.py
dvnv/dvnv.py
dvnv/scripts/all/create_dir.py
dvnv/scripts/all/create_readme.py
dvnv/scripts/all/gitignore.py
dvnv/scripts/python/new_dir.py
dvnv/scripts/python/poetry_init.sh
dvnv/scripts/vim/create_plugin_template.py
dvnv/utils.py
dvnv-0.4.1.dist-info/entry_points.txt
dvnv-0.4.1.dist-info/LICENSE
dvnv-0.4.1.dist-info/WHEEL
dvnv-0.4.1.dist-info/METADATA
dvnv-0.4.1.dist-info/RECORD
